unicorn-2.1.3.dist-info/WHEEL
unicorn-2.1.3.dist-info/RECORD
unicorn-2.1.3.dist-info/top_level.txt
unicorn-2.1.3.dist-info/METADATA
unicorn/x86_const.py
unicorn/s390x_const.py
unicorn/tricore_const.py
unicorn/py.typed
unicorn/arm64_const.py
unicorn/ppc_const.py
unicorn/arm_const.py
unicorn/__init__.py
unicorn/mips_const.py
unicorn/riscv_const.py
unicorn/unicorn.py
unicorn/unicorn_py2.py
unicorn/m68k_const.py
unicorn/sparc_const.py
unicorn/unicorn_const.py
unicorn/unicorn_py3/__init__.py
unicorn/unicorn_py3/unicorn.py
unicorn/unicorn_py3/arch/arm64.py
unicorn/unicorn_py3/arch/arm.py
unicorn/unicorn_py3/arch/__init__.py
unicorn/unicorn_py3/arch/intel.py
unicorn/unicorn_py3/arch/types.py
unicorn/include/unicorn/mips.h
unicorn/include/unicorn/tricore.h
unicorn/include/unicorn/platform.h
unicorn/include/unicorn/arm.h
unicorn/include/unicorn/riscv.h
unicorn/include/unicorn/arm64.h
unicorn/include/unicorn/unicorn.h
unicorn/include/unicorn/x86.h
unicorn/include/unicorn/sparc.h
unicorn/include/unicorn/s390x.h
unicorn/include/unicorn/m68k.h
unicorn/include/unicorn/ppc.h
unicorn/lib/libunicorn.a
unicorn/lib/libunicorn.so.2
