Metadata-Version: 2.1
Name: unicorn
Version: 2.1.3
Summary: Unicorn CPU emulator engine
Author-email: Nguyen Anh Quynh <quynh@gmail.com>
License: BSD License
Project-URL: Homepage, http://www.unicorn-engine.org
Project-URL: Repository, https://github.com/unicorn-engine/unicorn
Project-URL: Bug Tracker, https://github.com/unicorn-engine/unicorn/issues
Project-URL: Changelog, https://github.com/unicorn-engine/unicorn/blob/master/ChangeLog
Keywords: emulation,qemu,unicorn
Classifier: License :: OSI Approved :: BSD License
Classifier: Programming Language :: Python :: 2.7
Classifier: Programming Language :: Python :: 3.7
Classifier: Programming Language :: Python :: 3.8
Classifier: Programming Language :: Python :: 3.9
Classifier: Programming Language :: Python :: 3.10
Classifier: Programming Language :: Python :: 3.11
Classifier: Programming Language :: Python :: 3.12
Classifier: Programming Language :: Python :: 3.13
Requires-Python: !=3.0.*,!=3.1.*,!=3.2.*,!=3.3.*,!=3.4.*,!=3.5.*,!=3.6.*,>=2.7
Requires-Dist: importlib-resources ; python_version < "3.9"
Provides-Extra: test
Requires-Dist: capstone ==5.0.1 ; (python_version <= "3.7") and extra == 'test'
Requires-Dist: capstone ==6.0.0a2 ; (python_version > "3.7") and extra == 'test'
